battray/__init__.py
battray/platforms.py
battray/sound.py
battray-2.3.data/data/share/battray/alert.wav
battray-2.3.data/data/share/battray/battery.png
battray-2.3.data/data/share/battray/battrayrc.py
battray-2.3.data/data/share/battray/charging.png
battray-2.3.data/data/share/battray/connected.png
battray-2.3.data/data/share/battray/error.png
battray-2.3.data/data/share/battray/icon.png
battray-2.3.data/scripts/battray
battray-2.3.dist-info/DESCRIPTION.rst
battray-2.3.dist-info/METADATA
battray-2.3.dist-info/RECORD
battray-2.3.dist-info/WHEEL
battray-2.3.dist-info/metadata.json
battray-2.3.dist-info/top_level.txt
