Metadata-Version: 2.0
Name: battray
Version: 2.3
Summary: simple tray icon to show your laptop’s battery status.
Home-page: http://arp242.net/code/battray
Author: Martin Tournoij
Author-email: martin@arp242.net
License: MIT
Platform: UNKNOWN
Classifier: Development Status :: 5 - Production/Stable
Classifier: License :: OSI Approved :: MIT License
Classifier: Operating System :: POSIX
Classifier: Programming Language :: Python :: 3
Classifier: Programming Language :: Python :: 3.3
Classifier: Programming Language :: Python :: 3.4
Classifier: Programming Language :: Python :: 3.5
Classifier: Programming Language :: Python :: 3.6
Requires-Dist: pygobject
